w32py/__init__.py
w32py/ebest.py
w32py/korea.py
w32py/psutil.py
w32py/py.typed
w32py/win.py
w32py/winauto.py
w32py-0.3.6.dist-info/LICENSE
w32py-0.3.6.dist-info/WHEEL
w32py-0.3.6.dist-info/METADATA
w32py-0.3.6.dist-info/RECORD
