Metadata-Version: 2.1
Name: w32py
Version: 0.3.6
Summary: Python Win32 API
Author-email: Tom <nanticj@users.noreply.github.com>
Requires-Python: >=3.10
Classifier: License :: OSI Approved :: MIT License
Requires-Dist: PyQt5 >=5.15,<5.16
Requires-Dist: loguru >=0.6,<0.7
Requires-Dist: psutil >=5.9,<5.10
Requires-Dist: pywin32 >=305,<306
Requires-Dist: pywinauto >=0.6,<0.7
Requires-Dist: black >=23.1,<23.2 ; extra == "develop"
Requires-Dist: isort >=5.12,<5.13 ; extra == "develop"
Requires-Dist: mypy >=1.0,<1.1 ; extra == "develop"
Requires-Dist: pylint >=2.17,<2.18 ; extra == "develop"
Requires-Dist: pytest >=7.2,<7.3 ; extra == "develop"
Requires-Dist: types-pytz >=2022.7,<2022.8 ; extra == "develop"
Project-URL: Home, https://github.com/nanticj/w32py
Provides-Extra: develop
